celeste_openai/__init__.py
celeste_openai/py.typed
celeste_openai/audio/__init__.py
celeste_openai/audio/client.py
celeste_openai/audio/config.py
celeste_openai/audio/parameters.py
celeste_openai/images/__init__.py
celeste_openai/images/client.py
celeste_openai/images/config.py
celeste_openai/images/parameters.py
celeste_openai/images/streaming.py
celeste_openai/responses/__init__.py
celeste_openai/responses/client.py
celeste_openai/responses/config.py
celeste_openai/responses/parameters.py
celeste_openai/responses/streaming.py
celeste_openai/videos/__init__.py
celeste_openai/videos/client.py
celeste_openai/videos/config.py
celeste_openai/videos/parameters.py
celeste_openai-0.3.6.dist-info/METADATA
celeste_openai-0.3.6.dist-info/WHEEL
celeste_openai-0.3.6.dist-info/RECORD
